idu_kafka_client/__init__.py
idu_kafka_client/avro/__init__.py
idu_kafka_client/avro/model.py
idu_kafka_client/avro/serializer.py
idu_kafka_client/consumer/__init__.py
idu_kafka_client/consumer/handlers/__init__.py
idu_kafka_client/consumer/handlers/base.py
idu_kafka_client/consumer/handlers/registry.py
idu_kafka_client/consumer/service.py
idu_kafka_client/consumer/worker.py
idu_kafka_client/models/__init__.py
idu_kafka_client/producer/__init__.py
idu_kafka_client/producer/producer.py
idu_kafka_client/settings/__init__.py
idu_kafka_client/settings/base.py
idu_kafka_client/settings/consumer.py
idu_kafka_client/settings/producer.py
idu_kafka_client/utils/__init__.py
idu_kafka_client/utils/logger.py
idu_kafka_client-0.1.0.dist-info/LICENSE
idu_kafka_client-0.1.0.dist-info/METADATA
idu_kafka_client-0.1.0.dist-info/WHEEL
idu_kafka_client-0.1.0.dist-info/RECORD
