Metadata-Version: 2.1
Name: idu-kafka-client
Version: 0.1.0
Summary: Framework with scalable Kafka consumer/producer logic for IDU FastAPI services.
License: Apache-2.0
Author: Ruslan Babayev
Author-email: rus.babaef@yandex.ru
Requires-Python: >=3.11,<4.0
Classifier: License :: OSI Approved :: Apache Software License
Classifier: Programming Language :: Python :: 3
Classifier: Programming Language :: Python :: 3.11
Classifier: Programming Language :: Python :: 3.12
Requires-Dist: confluent-kafka[schemaregistry] (>=2.10.0,<3.0.0)
Requires-Dist: fastavro (>=1.10.0,<2.0.0)
Requires-Dist: pydantic (>=2.11.3,<3.0.0)
Requires-Dist: python-dotenv (>=1.1.0,<2.0.0)
Requires-Dist: pyyaml (>=6.0.2,<7.0.0)
